house_price_prediction/__init__.py
house_price_prediction/ingest_data.py
house_price_prediction/score.py
house_price_prediction/train.py
house_price_prediction_6112-0.1.dist-info/METADATA
house_price_prediction_6112-0.1.dist-info/WHEEL
house_price_prediction_6112-0.1.dist-info/entry_points.txt
house_price_prediction_6112-0.1.dist-info/top_level.txt
house_price_prediction_6112-0.1.dist-info/RECORD
