Metadata-Version: 2.1
Name: house_price_prediction_6112
Version: 0.1
Author-email: Snehita <sai.kanthamneni@tigeranalytics.com>
Project-URL: Homepage, https://github.com/snehita7k/mle-training
Requires-Dist: numpy
Requires-Dist: pandas
Requires-Dist: scikit-learn
Requires-Dist: scipy
